bubble_all_around/__init__.py
bubble_all_around/script.py
order_of_the_bubble-0.1.dist-info/METADATA
order_of_the_bubble-0.1.dist-info/WHEEL
order_of_the_bubble-0.1.dist-info/top_level.txt
order_of_the_bubble-0.1.dist-info/RECORD
